pixi/__init__.py
pixi/constants_globs.py
pixi/logger.py
pixi/main.py
pixi/setup_llvm.py
pixi/static_analyzer.py
pixi/utils.py
pixi/constants/__init__.py
pixi/constants/llvm_transform_src/__init__.py
py_pixi-0.0.1.dist-info/licenses/LICENSE
py_pixi-0.0.1.dist-info/METADATA
py_pixi-0.0.1.dist-info/WHEEL
py_pixi-0.0.1.dist-info/entry_points.txt
py_pixi-0.0.1.dist-info/top_level.txt
py_pixi-0.0.1.dist-info/RECORD
