Metadata-Version: 2.4
Name: py-pixi
Version: 0.0.1
Summary: A Python package for program analysis and custom instruction generation
Home-page: https://github.com/JoyenBenitto/Pixi
Author: Joyen Benitto
Author-email: joyen.benitto12@gmail.com
Classifier: Programming Language :: Python :: 3
Classifier: License :: OSI Approved :: MIT License
Classifier: Operating System :: OS Independent
Requires-Python: >=3.6
License-File: LICENSE
Dynamic: author
Dynamic: author-email
Dynamic: classifier
Dynamic: description
Dynamic: description-content-type
Dynamic: home-page
Dynamic: license-file
Dynamic: requires-python
Dynamic: summary
